dockflow/__init__.py
dockflow/cli.py
dockflow-1.2.0.dist-info/LICENSE
dockflow-1.2.0.dist-info/METADATA
dockflow-1.2.0.dist-info/WHEEL
dockflow-1.2.0.dist-info/dependency_links.txt
dockflow-1.2.0.dist-info/entry_points.txt
dockflow-1.2.0.dist-info/top_level.txt
dockflow-1.2.0.dist-info/RECORD
