Metadata-Version: 2.1
Name: dockflow
Version: 1.2.0
Summary: Easily deploy Airflow for local development
Home-page: https://gitlab.com/spatialedge/public/dockflow
Author: Pieter van der Westhuizen
Author-email: pieter@spatialedge.co.za
License: Spatialedge Community License
Platform: UNKNOWN
Classifier: Programming Language :: Python :: 3
Classifier: Operating System :: OS Independent
Requires-Python: >=3.6
License-File: LICENSE
Requires-Dist: click>=8.1.3
Requires-Dist: docker>=4.2.2
